neo4j_cypher/__init__.py
neo4j_cypher/chain.py
neo4j_cypher/selector.py
neo4j_cypher-0.1.1.dist-info/METADATA
neo4j_cypher-0.1.1.dist-info/WHEEL
neo4j_cypher-0.1.1.dist-info/RECORD
