Metadata-Version: 2.1
Name: neo4j-cypher
Version: 0.1.1
Summary: Natural language interface for a Neo4j graph database
Author: Tomaz Bratanic
Author-email: tomaz.bratanic@neo4j.com
Requires-Python: >=3.9,<4.0
Classifier: Programming Language :: Python :: 3
Classifier: Programming Language :: Python :: 3.9
Classifier: Programming Language :: Python :: 3.10
Classifier: Programming Language :: Python :: 3.11
Classifier: Programming Language :: Python :: 3.12
Requires-Dist: chromadb (>=0.5.5,<0.6.0)
Requires-Dist: langchain (>=0.2.13,<0.3.0)
Requires-Dist: langchain-aws (>=0.1.16,<0.2.0)
Requires-Dist: langchain-community (>=0.2.12,<0.3.0)
Requires-Dist: langchain-openai (>=0.1.21,<0.2.0)
Requires-Dist: neo4j (>=5.23.1,<6.0.0)
Requires-Dist: numpy (>=1.26.0,<2.0.0)
Requires-Dist: openai (>=1.40.6,<2.0.0)
